omnilog/omnilogd.py
omnilog/sshh.py
omnilog/parser.py
omnilog/__init__.py
omnilog/handler.py
omnilog/notifier.py
omnilog/strings.py
omnilog/ipcmessage.py
omnilog/logmessage.py
omnilog/wpanel.py
omnilog/cwatcher.py
omnilog/config.py
omnilog/logger.py
omnilog/ipcactions.py
omnilog/server.py
omnilog-0.9.0.dist-info/RECORD
omnilog-0.9.0.dist-info/WHEEL
omnilog-0.9.0.dist-info/top_level.txt
omnilog-0.9.0.dist-info/METADATA
omnilog-0.9.0.dist-info/metadata.json
omnilog-0.9.0.dist-info/DESCRIPTION.rst
omnilog-0.9.0.data/scripts/omnilogd.py
