Metadata-Version: 2.0
Name: omnilog
Version: 0.9.0
Summary: A remote log watcher daemon that uses ssh, and multithreaded design.
Home-page: https://github.com/sandboxwebs/omnilog
Author: Eloy (sbw)
Author-email: eloy@sandboxwebs.com
License: GPLV3
Download-URL: https://github.com/sandboxwebs/omnilog/tarball/0.9.0
Platform: any
Classifier: Programming Language :: Python :: 3 :: Only
Classifier: Development Status :: 4 - Beta
Classifier: Natural Language :: English
Classifier: Environment :: Console
Classifier: Intended Audience :: Developers
Classifier: Intended Audience :: System Administrators
Classifier: License :: Freely Distributable
Classifier: Operating System :: POSIX :: Linux
Classifier: Topic :: System :: Logging
Classifier: Topic :: System :: Monitoring
Requires-Dist: pytest
Requires-Dist: paramiko
Requires-Dist: notify2
